{
  "version": "7",
  "dialect": "mysql",
  "entries": [
    {
      "idx": 0,
      "version": "5",
      "when": 1770659472791,
      "tag": "0000_messy_madame_web",
      "breakpoints": true
    },
    {
      "idx": 1,
      "version": "5",
      "when": 1770660151684,
      "tag": "0001_chubby_proteus",
      "breakpoints": true
    },
    {
      "idx": 2,
      "version": "5",
      "when": 1770660989860,
      "tag": "0002_oval_blacklash",
      "breakpoints": true
    },
    {
      "idx": 3,
      "version": "5",
      "when": 1770661195861,
      "tag": "0003_mature_sandman",
      "breakpoints": true
    },
    {
      "idx": 4,
      "version": "5",
      "when": 1770738892888,
      "tag": "0004_greedy_susan_delgado",
      "breakpoints": true
    },
    {
      "idx": 5,
      "version": "5",
      "when": 1770744175126,
      "tag": "0005_nostalgic_jane_foster",
      "breakpoints": true
    },
    {
      "idx": 6,
      "version": "5",
      "when": 1770755400000,
      "tag": "0006_drop_partner_tables",
      "breakpoints": true
    },
    {
      "idx": 7,
      "version": "5",
      "when": 1770755401000,
      "tag": "0007_recreate_partner_tables",
      "breakpoints": true
    },
    {
      "idx": 8,
      "version": "5",
      "when": 1770757628658,
      "tag": "0008_thankful_songbird",
      "breakpoints": true
    },
    {
      "idx": 9,
      "version": "5",
      "when": 1770763796858,
      "tag": "0009_smart_madame_hydra",
      "breakpoints": true
    },
    {
      "idx": 10,
      "version": "5",
      "when": 1770819604265,
      "tag": "0010_wild_silver_fox",
      "breakpoints": true
    },
    {
      "idx": 11,
      "version": "5",
      "when": 1775412386883,
      "tag": "0011_lonely_nextwave",
      "breakpoints": true
    }
  ]
}